ambiegen/__init__.py
ambiegen/common/calc_novelty.py
ambiegen/common/cliffsDelta.py
ambiegen/common/duplicate_removal.py
ambiegen/common/get_convergence.py
ambiegen/common/get_stats.py
ambiegen/common/get_test_suite.py
ambiegen/common/kinematic_model.py
ambiegen/common/lane_controller.py
ambiegen/common/load_config.py
ambiegen/common/parse_arguments.py
ambiegen/common/random_seed.py
ambiegen/common/road_validity_check.py
ambiegen/common/rrt.py
ambiegen/common/save_tc_results.py
ambiegen/common/save_tcs_images.py
ambiegen/common/testcase.py
ambiegen/common/vehicle_evaluate.py
ambiegen/crossover/__init__.py
ambiegen/crossover/abstract_crossover.py
ambiegen/crossover/one_point_crossover.py
ambiegen/executors/__init__.py
ambiegen/executors/abstract_executor.py
ambiegen/executors/ambiegen_uav_executor.py
ambiegen/executors/fake_executor.py
ambiegen/executors/obstacle_scene_executor.py
ambiegen/executors/rrt_executor.py
ambiegen/generators/__init__.py
ambiegen/generators/abstract_generator.py
ambiegen/generators/obstacle_generator.py
ambiegen/mutation/__init__.py
ambiegen/mutation/abstract_mutation.py
ambiegen/mutation/obstacle_mutation.py
ambiegen/mutation/uniform_mutation.py
ambiegen/problems/__init__.py
ambiegen/problems/abstract_problem.py
ambiegen/sampling/__init__.py
ambiegen/sampling/abstract_sampling.py
ambiegen/sampling/greedy_sampling.py
ambiegen/sampling/lhs_sampling.py
ambiegen/testers/__init__.py
ambiegen/testers/abstract_bayes_opt_tester.py
ambiegen/testers/abstract_evolutionary_tester.py
ambiegen/testers/abstract_evolutionary_tester_ask_tell.py
ambiegen/testers/abstract_fuzzing_tester.py
ambiegen/testers/abstract_tester.py
ambiegen/testers/uav_tester.py
ambiegen-0.0.4.dist-info/licenses/LICENSE
ambiegen-0.0.4.dist-info/METADATA
ambiegen-0.0.4.dist-info/WHEEL
ambiegen-0.0.4.dist-info/top_level.txt
ambiegen-0.0.4.dist-info/RECORD
