Metadata-Version: 2.4
Name: ambiegen
Version: 0.0.4
Summary: AmbieGen is a flexible and modular framework for automated scenario-based testing of autonomous robotic systems
Author-email: Dmytro Humeniuk <gumenyuk98@gmail.com>
License:                     GNU GENERAL PUBLIC LICENSE
Project-URL: Homepage, https://github.com/swat-lab-optimization/ambiegen
Requires-Python: >=3.10
License-File: LICENSE
Requires-Dist: pymoo==0.6.1.1
Requires-Dist: Shapely==1.8.4
Requires-Dist: pandas==2.2.3
Requires-Dist: numpy==1.23.2
Requires-Dist: tqdm==4.66.1
Requires-Dist: descartes==1.1.0
Requires-Dist: beamngpy==1.24
Requires-Dist: tensorboard==2.13.0
Requires-Dist: shimmy>=0.2.1b0
Requires-Dist: scipy==1.11.3
Requires-Dist: requests==2.28.1
Requires-Dist: pyparsing==3.2.0
Requires-Dist: click==8.1.7
Requires-Dist: cloudpickle==3.0.0
Requires-Dist: wandb==0.15.12
Requires-Dist: bagpy
Requires-Dist: black
Dynamic: license-file
